saml/_version.py
saml/client.py
saml/__init__.py
saml/signature.py
saml/schema/saml.py
saml/schema/samlp.py
saml/schema/types.py
saml/schema/utils.py
saml/schema/__init__.py
saml/schema/meta.py
saml/schema/base.py
saml-0.7.0.dist-info/top_level.txt
saml-0.7.0.dist-info/DESCRIPTION.rst
saml-0.7.0.dist-info/metadata.json
saml-0.7.0.dist-info/WHEEL
saml-0.7.0.dist-info/RECORD
saml-0.7.0.dist-info/METADATA
